chatgpt/__init__.py
chatgpt/chatgpt.py
chatgpt_wrapper-0.0.1.dist-info/LICENSE
chatgpt_wrapper-0.0.1.dist-info/METADATA
chatgpt_wrapper-0.0.1.dist-info/WHEEL
chatgpt_wrapper-0.0.1.dist-info/top_level.txt
chatgpt_wrapper-0.0.1.dist-info/RECORD
