Metadata-Version: 2.1
Name: chatgpt-wrapper
Version: 0.0.1
Summary: A wrapper for chatgpt with logging, caching and more pythonic output parsing
Home-page: https://github.com/Globe-Knowledge-Solutions/chatgpt
Author: Ivan Yevenko
Author-email: ivan@globe.engineer
License: MIT
License-File: LICENSE
